knowmath/__init__.py
knowmath-0.0.1.dist-info/LICENSE
knowmath-0.0.1.dist-info/METADATA
knowmath-0.0.1.dist-info/WHEEL
knowmath-0.0.1.dist-info/top_level.txt
knowmath-0.0.1.dist-info/RECORD
