Metadata-Version: 2.1
Name: knowmath
Version: 0.0.1
Summary: Package used to perform general math operations
Author-email: Brandon Sexton <brandon.sexton.1@outlook.com>
License: GNU GENERAL PUBLIC LICENSE
Requires-Python: >=3.8
License-File: LICENSE
Provides-Extra: dev
Requires-Dist: black ; extra == 'dev'
Requires-Dist: pre-commit ; extra == 'dev'
Requires-Dist: isort ; extra == 'dev'
Requires-Dist: mypy ; extra == 'dev'
Requires-Dist: flake8 ; extra == 'dev'
